setup.cfg
setup.py
lesson_4/__init__.py
lesson_4/client.py
lesson_4/client_database.py
lesson_4/decos.py
lesson_4/descryptors.py
lesson_4/errors.py
lesson_4/launcher.py
lesson_4/launcher_gui.py
lesson_4/lesson_4.py
lesson_4/metaclasses.py
lesson_4/server.py
lesson_4/server_database.py
lesson_4/server_gui.py
lesson_4/test_client.py
lesson_4/test_server.py
lesson_4/test_utils.py
lesson_4.egg-info/PKG-INFO
lesson_4.egg-info/SOURCES.txt
lesson_4.egg-info/dependency_links.txt
lesson_4.egg-info/not-zip-safe
lesson_4.egg-info/top_level.txt