Metadata-Version: 2.1
Name: lesson-4
Version: 0.0
Summary: qwerty
Home-page: UNKNOWN
Author-email: natalya.bystrova.93@mail.ru
License: UNKNOWN
Platform: UNKNOWN
